pas_l10n/__init__.py
pas_l10n/l10n.py
pas_l10n/l10n_instance.py
pas_l10n/l10n_template.py
pas_l10n/number_formatter.py
pas_l10n/translatable_exception.py
pas_l10n-1.0.0.data/data/docs/LICENSE
pas_l10n-1.0.0.data/data/docs/README
pas_l10n-1.0.0.data/data/lang/de/pas.json
pas_l10n-1.0.0.data/data/lang/de_formal/pas.json
pas_l10n-1.0.0.data/data/lang/en/pas.json
pas_l10n-1.0.0.dist-info/LICENSE
pas_l10n-1.0.0.dist-info/METADATA
pas_l10n-1.0.0.dist-info/WHEEL
pas_l10n-1.0.0.dist-info/top_level.txt
pas_l10n-1.0.0.dist-info/RECORD
