Metadata-Version: 2.1
Name: pas-l10n
Version: 1.0.0
Summary: Python Application Services: Localization
Home-page: https://www.direct-netware.de/redirect?pas;l10n
Author: direct Netware Group et al.
Author-email: web@direct-netware.de
License: MPL2
Platform: any
Classifier: Intended Audience :: Developers
Classifier: License :: OSI Approved :: Mozilla Public License 2.0 (MPL 2.0)
Classifier: Operating System :: OS Independent
Classifier: Programming Language :: Python
Classifier: Topic :: Software Development :: Libraries :: Python Modules
Requires-Dist: dpt-cache (<2,>=1)
Requires-Dist: dpt-runtime (<2,>=1)
Requires-Dist: dpt-settings (<2,>=1)
Requires-Dist: dpt-threading (<2,>=1)
